readonly/__init__.py
readonly/context_processors.py
readonly/cursor.py
readonly/exceptions.py
readonly/middleware.py
django_db_readonly-0.7.0.dist-info/AUTHORS
django_db_readonly-0.7.0.dist-info/LICENSE
django_db_readonly-0.7.0.dist-info/METADATA
django_db_readonly-0.7.0.dist-info/WHEEL
django_db_readonly-0.7.0.dist-info/top_level.txt
django_db_readonly-0.7.0.dist-info/RECORD
