Metadata-Version: 2.1
Name: django-db-readonly
Version: 0.7.0
Summary: Add a global database read-only setting.
Home-page: https://github.com/streeter/django-db-readonly
Author: Chris Streeter
Author-email: pypi@chrisstreeter.com
License: MIT
Keywords: django database readonly
Platform: UNKNOWN
Classifier: Programming Language :: Python :: 2
Classifier: License :: OSI Approved :: MIT License
Classifier: Operating System :: OS Independent
Requires-Dist: Django (>=1.9)
Provides-Extra: test
Requires-Dist: pytest ; extra == 'test'
Requires-Dist: pytest-django ; extra == 'test'
Requires-Dist: flake8 ; extra == 'test'
